README.rst
setup.py
bin/greate
greate/__init__.py
greate.egg-info/PKG-INFO
greate.egg-info/SOURCES.txt
greate.egg-info/dependency_links.txt
greate.egg-info/requires.txt
greate.egg-info/top_level.txt