Metadata-Version: 1.0
Name: greate
Version: 0.1
Summary: UNKNOWN
Home-page: https://pypi.python.org/pypi/greate
Author: Yash Mehrotra
Author-email: yashmehrotra95@gmail.com
License: Apache 2.0
Platform: UNKNOWN
